str_case_util-1.0.0.dist-info/METADATA
str_case_util-1.0.0.dist-info/WHEEL
str_case_util-1.0.0.dist-info/entry_points.txt
str_case_util/__init__.py
str_case_util-1.0.0.dist-info/RECORD
