Metadata-Version: 2.1
Name: Str-Case-Util
Version: 1.0.0
Summary: Detect and convert string cases
Keywords: format,detect,determine,capital,capitalize,capitalization,upper,lower,title,snake,pascal,camel,kebab,caterpillar,cobol,str,string,util,utility,case,casing
Author-Email: Cody M Sommer <bassmastacod@gmail.com>
License: MIT
Classifier: License :: OSI Approved :: MIT License
Classifier: Programming Language :: Python :: 2.7
Classifier: Programming Language :: Python :: 3
Classifier: Programming Language :: Python :: 3.0
Classifier: Programming Language :: Python :: 3.1
Classifier: Programming Language :: Python :: 3.2
Classifier: Programming Language :: Python :: 3.3
Classifier: Programming Language :: Python :: 3.4
Classifier: Programming Language :: Python :: 3.5
Classifier: Programming Language :: Python :: 3.6
Classifier: Programming Language :: Python :: 3.7
Classifier: Programming Language :: Python :: 3.8
Classifier: Programming Language :: Python :: 3.9
Classifier: Programming Language :: Python :: 3.10
Classifier: Programming Language :: Python :: 3.11
Classifier: Programming Language :: Python :: 3.12
Classifier: Programming Language :: Python :: 3.13
Classifier: Programming Language :: Python :: 3.14
Classifier: Development Status :: 5 - Production/Stable
Classifier: Intended Audience :: Developers
Classifier: Topic :: Software Development :: Libraries
Classifier: Typing :: Typed
Project-URL: Repository, https://github.com/BassMastaCod/Str-Case-Util.git
Project-URL: Issues, https://github.com/BassMastaCod/Str-Case-Util/issues
Requires-Python: >=2.7
